MANIFEST.in
README.md
setup.py
django_rosetta_inpage.egg-info/PKG-INFO
django_rosetta_inpage.egg-info/SOURCES.txt
django_rosetta_inpage.egg-info/dependency_links.txt
django_rosetta_inpage.egg-info/not-zip-safe
django_rosetta_inpage.egg-info/requires.txt
django_rosetta_inpage.egg-info/top_level.txt
rosetta_inpage/__init__.py
rosetta_inpage/conf.py
rosetta_inpage/middleware.py
rosetta_inpage/patches.py
rosetta_inpage/urls.py
rosetta_inpage/utils.py
rosetta_inpage/views.py
rosetta_inpage/static/rosetta_inpage/config.rb
rosetta_inpage/static/rosetta_inpage/.sass-cache/54ce692b105b96aab41a119b589956942ad04086/inpage.scssc
rosetta_inpage/static/rosetta_inpage/css/inpage.css
rosetta_inpage/static/rosetta_inpage/img/pacman.gif
rosetta_inpage/static/rosetta_inpage/img/squirrel.png
rosetta_inpage/static/rosetta_inpage/img/glyphicons/glyphicons_081_refresh.png
rosetta_inpage/static/rosetta_inpage/img/glyphicons/glyphicons_207_remove.png
rosetta_inpage/static/rosetta_inpage/img/glyphicons/glyphicons_340_globe.png
rosetta_inpage/static/rosetta_inpage/img/glyphicons/glyphicons_355_bullhorn.png
rosetta_inpage/static/rosetta_inpage/img/glyphicons/glyphicons_401_github.png
rosetta_inpage/static/rosetta_inpage/js/inpage.js
rosetta_inpage/static/rosetta_inpage/sass/inpage.scss
rosetta_inpage/templates/rosetta_inpage/form.html
rosetta_inpage/templates/rosetta_inpage/sidebar.html
rosetta_inpage/tests/__init__.py