Metadata-Version: 1.0
Name: django-rosetta-inpage
Version: 0.0.9
Summary: Translate i18n messages with Django Rosetta
Home-page: http://github.com/citylive/django-rosetta-inpage/
Author: Maarten Huijsmans, VikingCo NV
Author-email: maarten.huijsmans@mobilevikings.com
License: BSD
Platform: UNKNOWN
Classifier: Development Status :: 2 - Pre-Alpha
Classifier: Intended Audience :: Developers
Classifier: License :: OSI Approved :: BSD License
Classifier: Programming Language :: Python
Classifier: Operating System :: OS Independent
Classifier: Environment :: Web Environment
Classifier: Framework :: Django
Classifier: Topic :: Software Development :: Internationalization
